portpicker.py
portpicker-1.6.0.data/scripts/portserver.py
portpicker-1.6.0.dist-info/LICENSE
portpicker-1.6.0.dist-info/METADATA
portpicker-1.6.0.dist-info/WHEEL
portpicker-1.6.0.dist-info/top_level.txt
portpicker-1.6.0.dist-info/RECORD
